[
{"name" : "MF-2056"},
{"name" : "MF-2055"},
{"name" : "MF-2058"},
{"name" : "MF-2059"},
{"name" : "MF-2057"},
{"name" : "MF-2051"},
{"name" : "MF-2052"},
{"name" : "MF-2050"},
{"name" : "MF-2054"},
{"name" : "MF-2053"},
{"name" : "MF-2064"},
{"name" : "MF-2065"},
{"name" : "MF-2063"},
{"name" : "MF-2066"},
{"name" : "MF-2067"},
{"name" : "MF-2061"},
{"name" : "MF-2060"},
{"name" : "MF-2062"},
{"name" : "MF-2039"},
{"name" : "MF-2038"},
{"name" : "MF-2042"},
{"name" : "MF-2040"},
{"name" : "MF-2041"},
{"name" : "MF-2034"},
{"name" : "MF-2035"},
{"name" : "MF-2033"},
{"name" : "MF-2037"},
{"name" : "MF-2036"},
{"name" : "MF-2047"},
{"name" : "MF-2046"},
{"name" : "MF-2049"},
{"name" : "MF-2048"},
{"name" : "MF-2043"},
{"name" : "MF-2044"},
{"name" : "MF-2045"},
{"name" : "MF-2088"},
{"name" : "MF-2089"},
{"name" : "MF-2087"},
{"name" : "MF-2091"},
{"name" : "MF-2092"},
{"name" : "MF-2090"},
{"name" : "MF-2084"},
{"name" : "MF-2083"},
{"name" : "MF-2086"},
{"name" : "MF-2085"},
{"name" : "MF-2097"},
{"name" : "MF-2098"},
{"name" : "MF-2096"},
{"name" : "MF-2099"},
{"name" : "MF-2093"},
{"name" : "MF-2095"},
{"name" : "MF-2094"},
{"name" : "MF-2072"},
{"name" : "MF-2071"},
{"name" : "MF-2070"},
{"name" : "MF-2073"},
{"name" : "MF-2074"},
{"name" : "MF-2068"},
{"name" : "MF-2069"},
{"name" : "MF-2080"},
{"name" : "MF-2079"},
{"name" : "MF-2082"},
{"name" : "MF-2081"},
{"name" : "MF-2075"},
{"name" : "MF-2076"},
{"name" : "MF-2078"},
{"name" : "MF-2077"},
{"name" : "MF-2001"},
{"name" : "MF-501"},
{"name" : "MF-2002"},
{"name" : "MF-2003"},
{"name" : "MF-2006"},
{"name" : "MF-2005"},
{"name" : "MF-2007"},
{"name" : "MF-2008"},
{"name" : "MF-2004"},
{"name" : "MF-460"},
{"name" : "MF-461"},
{"name" : "MF-459"},
{"name" : "MF-463"},
{"name" : "MF-462"},
{"name" : "MF-455"},
{"name" : "MF-457"},
{"name" : "MF-453"},
{"name" : "MF-458"},
{"name" : "MF-477"},
{"name" : "MF-481"},
{"name" : "MF-485"},
{"name" : "MF-464"},
{"name" : "MF-465"},
{"name" : "MF-469"},
{"name" : "MF-472"},
{"name" : "MF-2023"},
{"name" : "MF-2022"},
{"name" : "MF-2025"},
{"name" : "MF-2024"},
{"name" : "MF-2020"},
{"name" : "MF-2018"},
{"name" : "MF-2021"},
{"name" : "MF-2030"},
{"name" : "MF-2031"},
{"name" : "MF-2029"},
{"name" : "MF-2032"},
{"name" : "MF-2026"},
{"name" : "MF-2027"},
{"name" : "MF-2028"},
{"name" : "MF-2011"},
{"name" : "MF-2012"},
{"name" : "MF-2009"},
{"name" : "MF-2010"},
{"name" : "MF-2016"},
{"name" : "MF-2017"},
{"name" : "MF-2015"},
{"name" : "MF-2013"},
{"name" : "MF-2014"},
{"name" : "MF-2194"},
{"name" : "MF-2192"},
{"name" : "MF-2193"},
{"name" : "MF-2195"},
{"name" : "MF-2196"},
{"name" : "MF-2189"},
{"name" : "MF-2188"},
{"name" : "MF-2191"},
{"name" : "MF-2190"},
{"name" : "MF-2204"},
{"name" : "MF-2203"},
{"name" : "MF-2202"},
{"name" : "MF-2206"},
{"name" : "MF-2207"},
{"name" : "MF-2205"},
{"name" : "MF-2198"},
{"name" : "MF-2199"},
{"name" : "MF-2197"},
{"name" : "MF-2201"},
{"name" : "MF-2200"},
{"name" : "MF-2175"},
{"name" : "MF-2176"},
{"name" : "MF-2174"},
{"name" : "MF-2178"},
{"name" : "MF-2177"},
{"name" : "MF-2171"},
{"name" : "MF-2172"},
{"name" : "MF-2170"},
{"name" : "MF-2173"},
{"name" : "MF-2185"},
{"name" : "MF-2186"},
{"name" : "MF-2184"},
{"name" : "MF-2187"},
{"name" : "MF-2181"},
{"name" : "MF-2180"},
{"name" : "MF-2183"},
{"name" : "MF-2182"},
{"name" : "MF-3053"},
{"name" : "MF-3054"},
{"name" : "MF-3051"},
{"name" : "MF-3052"},
{"name" : "MF-3056"},
{"name" : "MF-3055"},
{"name" : "MF-3046"},
{"name" : "MF-3049"},
{"name" : "MF-3045"},
{"name" : "MF-3050"},
{"name" : "MF-3080"},
{"name" : "MF-3079"},
{"name" : "MF-3081"},
{"name" : "MF-3058"},
{"name" : "MF-3060"},
{"name" : "MF-3057"},
{"name" : "MF-3064"},
{"name" : "MF-3065"},
{"name" : "MF-3061"},
{"name" : "MF-3063"},
{"name" : "MF-3062"},
{"name" : "MF-3022"},
{"name" : "MF-3021"},
{"name" : "MF-3027"},
{"name" : "MF-2210"},
{"name" : "MF-2211"},
{"name" : "MF-2208"},
{"name" : "MF-2209"},
{"name" : "MF-2213"},
{"name" : "MF-2212"},
{"name" : "MF-3041"},
{"name" : "MF-3039"},
{"name" : "MF-3044"},
{"name" : "MF-3035"},
{"name" : "MF-3033"},
{"name" : "MF-3034"},
{"name" : "MF-3038"},
{"name" : "MF-3037"},
{"name" : "MF-2122"},
{"name" : "MF-2123"},
{"name" : "MF-2121"},
{"name" : "MF-2125"},
{"name" : "MF-2124"},
{"name" : "MF-2117"},
{"name" : "MF-2116"},
{"name" : "MF-2115"},
{"name" : "MF-2119"},
{"name" : "MF-2118"},
{"name" : "MF-2130"},
{"name" : "MF-2131"},
{"name" : "MF-2129"},
{"name" : "MF-2126"},
{"name" : "MF-2127"},
{"name" : "MF-2128"},
{"name" : "MF-2104"},
{"name" : "MF-2103"},
{"name" : "MF-2106"},
{"name" : "MF-2107"},
{"name" : "MF-2105"},
{"name" : "MF-2100"},
{"name" : "MF-2101"},
{"name" : "MF-2102"},
{"name" : "MF-2112"},
{"name" : "MF-2113"},
{"name" : "MF-2111"},
{"name" : "MF-2114"},
{"name" : "MF-2108"},
{"name" : "MF-2110"},
{"name" : "MF-2157"},
{"name" : "MF-2158"},
{"name" : "MF-2156"},
{"name" : "MF-2159"},
{"name" : "MF-2160"},
{"name" : "MF-2153"},
{"name" : "MF-2152"},
{"name" : "MF-2151"},
{"name" : "MF-2155"},
{"name" : "MF-2154"},
{"name" : "MF-2167"},
{"name" : "MF-2166"},
{"name" : "MF-2165"},
{"name" : "MF-2169"},
{"name" : "MF-2168"},
{"name" : "MF-2162"},
{"name" : "MF-2161"},
{"name" : "MF-2164"},
{"name" : "MF-2163"},
{"name" : "MF-2139"},
{"name" : "MF-2140"},
{"name" : "MF-2138"},
{"name" : "MF-2142"},
{"name" : "MF-2141"},
{"name" : "MF-2136"},
{"name" : "MF-2135"},
{"name" : "MF-2137"},
{"name" : "MF-2148"},
{"name" : "MF-2149"},
{"name" : "MF-2147"},
{"name" : "MF-2150"},
{"name" : "MF-2144"},
{"name" : "MF-2143"},
{"name" : "MF-2145"},
{"name" : "MF-2146"},
{"name" : "MF-226"},
{"name" : "MF-229"},
{"name" : "MF-230"},
{"name" : "MF-223"},
{"name" : "MF-222"},
{"name" : "MF-225"},
{"name" : "MF-224"},
{"name" : "MF-235"},
{"name" : "MF-236"},
{"name" : "MF-237"},
{"name" : "MF-231"},
{"name" : "MF-232"},
{"name" : "MF-202"},
{"name" : "MF-201"},
{"name" : "MF-207"},
{"name" : "MF-208"},
{"name" : "MF-204"},
{"name" : "MF-198"},
{"name" : "MF-199"},
{"name" : "MF-200"},
{"name" : "MF-218"},
{"name" : "MF-215"},
{"name" : "MF-221"},
{"name" : "MF-219"},
{"name" : "MF-209"},
{"name" : "MF-214"},
{"name" : "MF-213"},
{"name" : "MF-271"},
{"name" : "MF-270"},
{"name" : "MF-274"},
{"name" : "MF-263"},
{"name" : "MF-261"},
{"name" : "MF-260"},
{"name" : "MF-268"},
{"name" : "MF-264"},
{"name" : "MF-267"},
{"name" : "MF-280"},
{"name" : "MF-284"},
{"name" : "MF-283"},
{"name" : "MF-276"},
{"name" : "MF-275"},
{"name" : "MF-278"},
{"name" : "MF-277"},
{"name" : "MF-245"},
{"name" : "MF-248"},
{"name" : "MF-247"},
{"name" : "MF-238"},
{"name" : "MF-239"},
{"name" : "MF-240"},
{"name" : "MF-258"},
{"name" : "MF-256"},
{"name" : "MF-257"},
{"name" : "MF-259"},
{"name" : "MF-251"},
{"name" : "MF-253"},
{"name" : "MF-113"},
{"name" : "MF-107"},
{"name" : "MF-115"},
{"name" : "MF-131"},
{"name" : "MF-130"},
{"name" : "MF-133"},
{"name" : "MF-132"},
{"name" : "MF-122"},
{"name" : "MF-123"},
{"name" : "MF-124"},
{"name" : "MF-292"},
{"name" : "MF-2"},
{"name" : "MF-9"},
{"name" : "MF-108"},
{"name" : "MF-3"},
{"name" : "MF-37"},
{"name" : "MF-24"},
{"name" : "MF-104"},
{"name" : "MF-101"},
{"name" : "MF-10"},
{"name" : "MF-176"},
{"name" : "MF-174"},
{"name" : "MF-187"},
{"name" : "MF-184"},
{"name" : "MF-171"},
{"name" : "MF-170"},
{"name" : "MF-173"},
{"name" : "MF-195"},
{"name" : "MF-194"},
{"name" : "MF-197"},
{"name" : "MF-196"},
{"name" : "MF-192"},
{"name" : "MF-188"},
{"name" : "MF-193"},
{"name" : "MF-142"},
{"name" : "MF-140"},
{"name" : "MF-141"},
{"name" : "MF-145"},
{"name" : "MF-135"},
{"name" : "MF-134"},
{"name" : "MF-139"},
{"name" : "MF-160"},
{"name" : "MF-159"},
{"name" : "MF-169"},
{"name" : "MF-168"},
{"name" : "MF-157"},
{"name" : "MF-156"},
{"name" : "MF-394"},
{"name" : "MF-393"},
{"name" : "MF-392"},
{"name" : "MF-396"},
{"name" : "MF-395"},
{"name" : "MF-389"},
{"name" : "MF-388"},
{"name" : "MF-390"},
{"name" : "MF-403"},
{"name" : "MF-401"},
{"name" : "MF-402"},
{"name" : "MF-406"},
{"name" : "MF-405"},
{"name" : "MF-404"},
{"name" : "MF-397"},
{"name" : "MF-399"},
{"name" : "MF-400"},
{"name" : "MF-372"},
{"name" : "MF-371"},
{"name" : "MF-370"},
{"name" : "MF-369"},
{"name" : "MF-373"},
{"name" : "MF-374"},
{"name" : "MF-366"},
{"name" : "MF-365"},
{"name" : "MF-363"},
{"name" : "MF-368"},
{"name" : "MF-367"},
{"name" : "MF-382"},
{"name" : "MF-383"},
{"name" : "MF-381"},
{"name" : "MF-384"},
{"name" : "MF-385"},
{"name" : "MF-377"},
{"name" : "MF-378"},
{"name" : "MF-376"},
{"name" : "MF-430"},
{"name" : "MF-431"},
{"name" : "MF-429"},
{"name" : "MF-433"},
{"name" : "MF-432"},
{"name" : "MF-426"},
{"name" : "MF-424"},
{"name" : "MF-428"},
{"name" : "MF-427"},
{"name" : "MF-444"},
{"name" : "MF-442"},
{"name" : "MF-443"},
{"name" : "MF-452"},
{"name" : "MF-445"},
{"name" : "MF-451"},
{"name" : "MF-436"},
{"name" : "MF-435"},
{"name" : "MF-437"},
{"name" : "MF-434"},
{"name" : "MF-441"},
{"name" : "MF-438"},
{"name" : "MF-413"},
{"name" : "MF-412"},
{"name" : "MF-411"},
{"name" : "MF-415"},
{"name" : "MF-416"},
{"name" : "MF-414"},
{"name" : "MF-407"},
{"name" : "MF-408"},
{"name" : "MF-410"},
{"name" : "MF-409"},
{"name" : "MF-422"},
{"name" : "MF-421"},
{"name" : "MF-423"},
{"name" : "MF-418"},
{"name" : "MF-417"},
{"name" : "MF-420"},
{"name" : "MF-419"},
{"name" : "MF-317"},
{"name" : "MF-316"},
{"name" : "MF-319"},
{"name" : "MF-318"},
{"name" : "MF-308"},
{"name" : "MF-312"},
{"name" : "MF-303"},
{"name" : "MF-314"},
{"name" : "MF-315"},
{"name" : "MF-313"},
{"name" : "MF-325"},
{"name" : "MF-326"},
{"name" : "MF-324"},
{"name" : "MF-323"},
{"name" : "MF-327"},
{"name" : "MF-321"},
{"name" : "MF-320"},
{"name" : "MF-322"},
{"name" : "MF-289"},
{"name" : "MF-291"},
{"name" : "MF-300"},
{"name" : "MF-298"},
{"name" : "MF-299"},
{"name" : "MF-302"},
{"name" : "MF-301"},
{"name" : "MF-294"},
{"name" : "MF-293"},
{"name" : "MF-351"},
{"name" : "MF-352"},
{"name" : "MF-350"},
{"name" : "MF-354"},
{"name" : "MF-355"},
{"name" : "MF-353"},
{"name" : "MF-345"},
{"name" : "MF-346"},
{"name" : "MF-344"},
{"name" : "MF-349"},
{"name" : "MF-348"},
{"name" : "MF-347"},
{"name" : "MF-361"},
{"name" : "MF-360"},
{"name" : "MF-362"},
{"name" : "MF-356"},
{"name" : "MF-358"},
{"name" : "MF-359"},
{"name" : "MF-357"},
{"name" : "MF-333"},
{"name" : "MF-332"},
{"name" : "MF-331"},
{"name" : "MF-335"},
{"name" : "MF-336"},
{"name" : "MF-334"},
{"name" : "MF-329"},
{"name" : "MF-328"},
{"name" : "MF-330"},
{"name" : "MF-341"},
{"name" : "MF-340"},
{"name" : "MF-339"},
{"name" : "MF-343"},
{"name" : "MF-342"},
{"name" : "MF-337"},
{"name" : "MF-338"},
{"name" : "MF-118"},
{"name" : "MF-51"},
{"name" : "MF-79"},
{"name" : "MF-306"},
{"name" : "MF-25"},
{"name" : "MF-1"},
{"name" : "MF-26"},
{"name" : "MF-23"},
{"name" : "MF-27"},
{"name" : "MF-53"},
{"name" : "MF-30"},
{"name" : "MF-28"},
{"name" : "MF-21"},
{"name" : "MF-116"},
{"name" : "MF-180"},
{"name" : "NO CONT"},
{"name" : "MF-163"},
{"name" : "MF-111"},
{"name" : "MF-83"},
{"name" : "MF-105"},
{"name" : "MF-5"},
{"name" : "MF-70"},
{"name" : "MF-97"},
{"name" : "MF-72"},
{"name" : "MF-73"},
{"name" : "MF-   "},
{"name" : "MF-14"},
{"name" : "MF-17"},
{"name" : "MF-20"},
{"name" : "MF-15"},
{"name" : "MF-12"},
{"name" : "MF-19"},
{"name" : "MF-18"},
{"name" : "MF-78"},
{"name" : "MF-39"},
{"name" : "MF-150"},
{"name" : "MF-148"},
{"name" : "MF-146"},
{"name" : "MF-86"},
{"name" : "MF-93"},
{"name" : "MF-80"},
{"name" : "MF-74"},
{"name" : "MF-75"},
{"name" : "MF-109"},
{"name" : "MF-34"},
{"name" : "MF-36"},
{"name" : "MF-31"},
{"name" : "MF-33"},
{"name" : "MF-136"},
{"name" : "MF-137"},
{"name" : "MF-4"},
{"name" : "MF-67"},
{"name" : "MF-62"},
{"name" : "MF-11"},
{"name" : "JFP-615"},
{"name" : "MF-13"},
{"name" : "2101"},
{"name" : "2100"},
{"name" : "2040"},
{"name" : "MF-"},
{"name" : "MF-48"},
{"name" : "  MF-2101  "},
{"name" : "MF-42"},
{"name" : "MF-  "},
{"name" : "MF-54"},
{"name" : "MF-46"},
{"name" : "MF-52"},
{"name" : "MF-55"},
{"name" : "MF-45"},
{"name" : "MF-90"},
{"name" : "MF-35"},
{"name" : "MF-41"},
{"name" : "MF-87"},
{"name" : "MF-69"},
{"name" : "MF-40"},
{"name" : "MF-47"},
{"name" : "MF-38"},
{"name" : "MF-8"},
{"name" : "MF-57"},
{"name" : "MF-94"},
{"name" : "MF-61"},
{"name" : " "},
{"name" : "MF-7"},
{"name" : "MF-29"},
{"name" : "MF-16"},
{"name" : "MF-49"},
{"name" : "MF-6"},
{"name" : "MF-149"},
{"name" : "MF-32"},
{"name" : "MF-183"},
{"name" : "MF-22"},
{"name" : "MF-152"},
{"name" : "MF- "},
{"name" : "-"},
{"name" : "MF-147"},
{"name" : "MF-88"},
{"name" : "MF-92"},
{"name" : "MF-106"},
{"name" : "MF-121"},
{"name" : "MF-60"},
{"name" : "MF-64"},
{"name" : "2089"},
{"name" : "MF-68"},
{"name" : "MF-110"},
{"name" : "MF-112"},
{"name" : "MF-503"},
{"name" : "MF-504"},
{"name" : "MF-506"},
{"name" : "MF-216"},
{"name" : "MF-205"},
{"name" : "MF-172"},
{"name" : "MF-103"},
{"name" : "MF-155"},
{"name" : "MF-161"},
{"name" : "MF-153"},
{"name" : "MF-127"},
{"name" : "MF-392   "},
{"name" : "MF-309"},
{"name" : "MF-305"},
{"name" : "MF-100"},
{"name" : "MF-182"},
{"name" : "MF-154"},
{"name" : "MF-162"},
{"name" : "MF-120"},
{"name" : "MF-128"},
{"name" : "MF-364"},
{"name" : "MF-151"},
{"name" : "MF-175"},
{"name" : "MF-165"},
{"name" : "MF-114"},
{"name" : "MF-380"},
{"name" : "MF394"},
{"name" : "SHEET"},
{"name" : "MF-158"},
{"name" : "MF-252"},
{"name" : "MF-119"},
{"name" : "MF-XXX"},
{"name" : "MF-181"},
{"name" : "MF 181"},
{"name" : "MF-125"},
{"name" : "MF-290"},
{"name" : "MF-44"},
{"name" : "MF-63"},
{"name" : "MF-3014"},
{"name" : "MF-56"},
{"name" : "NO CONT."},
{"name" : "MF-375"},
{"name" : "SHT. 11"},
{"name" : "MF-203"},
{"name" : "SH. 2"},
{"name" : "MF-117"},
{"name" : "MF-126"},
{"name" : "MF-287"},
{"name" : "MF-307"},
{"name" : "MF-254"},
{"name" : "MF-58"},
{"name" : "MF-391"},
{"name" : "MF-210"},
{"name" : "MF-249"},
{"name" : "MF-177"},
{"name" : "MF3055"},
{"name" : "MF-206"},
{"name" : "MF-012"},
{"name" : "MF-250"},
{"name" : "MF-50"},
{"name" : "MF-179"},
{"name" : "MF-77"},
{"name" : "MF-85"},
{"name" : "MF-84"},
{"name" : "MF-82"},
{"name" : "MF-217"},
{"name" : "MF-144"},
{"name" : "MF-178"},
{"name" : "MF-166"},
{"name" : "MF-129"},
{"name" : "MF-89"},
{"name" : "MF-164"},
{"name" : "MF-76"},
{"name" : "   NO CONT MF"},
{"name" : "MF-498"},
{"name" : "MF2176"},
{"name" : "NF-31"},
{"name" : "MF2173"},
{"name" : "MF-76/83"},
{"name" : "MF-xx"},
{"name" : "MF-0057"},
{"name" : "MF-0058"},
{"name" : "MF-0019"},
{"name" : "MF-0046"},
{"name" : "MF-0064"},
{"name" : "MF-102"},
{"name" : "MF-044"},
{"name" : "MF-2130 "},
{"name" : "MF-255"},
{"name" : "MF-212"},
{"name" : "MF-496"},
{"name" : "NOTE 2"},
{"name" : "MF-228"},
{"name" : "MF2164"},
{"name" : "MF-227"},
{"name" : "MF-220"},
{"name" : "MF-246"},
{"name" : "MF-143"},
{"name" : "MF-3025"},
{"name" : "MF-66"},
{"name" : "MF-189"},
{"name" : "A-73"},
{"name" : "MF-297"},
{"name" : "SHT.3452"},
{"name" : "MF-65"},
{"name" : "2065"},
{"name" : "MF 222"},
{"name" : "MF 223"},
{"name" : "MF-272"},
{"name" : "MF-262"},
{"name" : "MF-488"},
{"name" : "MF-281"},
{"name" : "SH.-4"},
{"name" : "MF-490"},
{"name" : "MF-111L"},
{"name" : "MF-3043"},
{"name" : "NOTE 6"},
{"name" : "MF-2126  "},
{"name" : "MF-2130  "},
{"name" : "MF-357  "},
{"name" : "MF-2115  "},
{"name" : "SHT. 28"},
{"name" : "MF-43"},
{"name" : "DN-45"},
{"name" : "MF-2093  "},
{"name" : "MF-2126 "},
{"name" : "MF-323  "},
{"name" : "MF-023"},
{"name" : "MF-93 "},
{"name" : "MF-005"},
{"name" : "MF-500"},
{"name" : "MF-273"},
{"name" : "P-90"},
{"name" : "P-69"},
{"name" : "JN-12"},
{"name" : "MF-473"},
{"name" : "DET. "B""},
{"name" : "DET."C""},
{"name" : "DN-4"},
{"name" : "D-250-70312"},
{"name" : "MF-3042"},
{"name" : "DN-19"},
{"name" : "MF-288"},
{"name" : "2167"},
{"name" : "MF-243"},
{"name" : "MF-234"},
{"name" : "MF-2186 "},
{"name" : "M-2097"}
]
